py_slack_notify/__init__.py
py_slack_notify/slack_notify.py
py_slack_notify-0.2.0.dist-info/METADATA
py_slack_notify-0.2.0.dist-info/WHEEL
py_slack_notify-0.2.0.dist-info/top_level.txt
py_slack_notify-0.2.0.dist-info/RECORD
