Metadata-Version: 2.1
Name: py-slack-notify
Version: 0.2.0
Summary: Python package for sending notification to Slack in thread with emoji
Home-page: UNKNOWN
Author: binhqd
Author-email: UNKNOWN
License: MIT
Platform: UNKNOWN
